mloq/__init__.py
mloq/__main__.py
mloq/_utils.py
mloq/cli.py
mloq/command.py
mloq/custom_click.py
mloq/failure.py
mloq/files.py
mloq/git.py
mloq/record.py
mloq/runner.py
mloq/templating.py
mloq/version.py
mloq/writer.py
mloq/assets/ci/push.yml
mloq/assets/docker/Dockerfile
mloq/assets/docker/Makefile.docker
mloq/assets/docs/conf.txt
mloq/assets/docs/deploy-docs.yml
mloq/assets/docs/index.md
mloq/assets/docs/make_bat.txt
mloq/assets/docs/makefile_docs.txt
mloq/assets/docs/requirements-docs.txt
mloq/assets/license/APACHE_LICENSE
mloq/assets/license/DCO.md
mloq/assets/license/GPL_LICENSE
mloq/assets/license/MIT_LICENSE
mloq/assets/lint/requirements-lint.txt
mloq/assets/mloq/WHAT_MLOQ_GENERATED.md
mloq/assets/mloq/mloq.yaml
mloq/assets/package/setup.txt
mloq/assets/project/.codecov.yml
mloq/assets/project/.gitignore
mloq/assets/project/.pre-commit-config.yaml
mloq/assets/project/CODE_OF_CONDUCT.md
mloq/assets/project/CONTRIBUTING.md
mloq/assets/project/init.txt
mloq/assets/project/main.txt
mloq/assets/project/requirements-test.txt
mloq/assets/project/test_main.txt
mloq/assets/project/version.txt
mloq/assets/requirements/data-science.txt
mloq/assets/requirements/data-visualization.txt
mloq/assets/requirements/dogfood.txt
mloq/assets/requirements/pytorch.txt
mloq/assets/requirements/requirements.txt
mloq/assets/requirements/tensorflow.txt
mloq/assets/shared/Makefile
mloq/assets/shared/README.md
mloq/assets/shared/pyproject.toml
mloq/commands/__init__.py
mloq/commands/ci.py
mloq/commands/docker.py
mloq/commands/docs.py
mloq/commands/globals.py
mloq/commands/license.py
mloq/commands/lint.py
mloq/commands/package.py
mloq/commands/project.py
mloq/commands/requirements.py
mloq/commands/setup.py
mloq/config/__init__.py
mloq/config/configuration.py
mloq/config/custom_click.py
mloq/config/param_patch.py
mloq/config/prompt.py
mloq-0.0.75.dist-info/LICENSE
mloq-0.0.75.dist-info/METADATA
mloq-0.0.75.dist-info/WHEEL
mloq-0.0.75.dist-info/entry_points.txt
mloq-0.0.75.dist-info/top_level.txt
mloq-0.0.75.dist-info/RECORD
