Metadata-Version: 2.1
Name: mloq
Version: 0.0.75
Summary: Package for initializing ML projects following ML Ops best practices.
Home-page: https://github.com/FragileTech/ml-ops-quickstart
Download-URL: https://github.com/FragileTech/ml-ops-quickstart/releases
Author: FragileTech
Author-email: guillem@fragile.tech
License: MIT
Keywords: Machine learning,artificial intelligence
Classifier: Development Status :: 3 - Alpha
Classifier: Environment :: Console
Classifier: Intended Audience :: Developers
Classifier: License :: OSI Approved :: MIT License
Classifier: Programming Language :: Python :: 3.6
Classifier: Programming Language :: Python :: 3.7
Classifier: Programming Language :: Python :: 3.8
Classifier: Programming Language :: Python :: 3.9
Classifier: Programming Language :: Python :: 3 :: Only
Classifier: Topic :: Software Development :: Libraries
License-File: LICENSE
Requires-Dist: flogging (>=0.0.14)
Requires-Dist: jinja2 (>=3.0.0)
Requires-Dist: click (>=8.0.0)
Requires-Dist: invoke (>=1.4.1)
Requires-Dist: hydra-core (>=1.1.1)
Requires-Dist: param (>=1.11.0)
Requires-Dist: pre-commit (>=2.15.0)
Requires-Dist: typing-extensions (>=4.0.0)
